README.md
setup.py
python3.5.egg-info/PKG-INFO
python3.5.egg-info/SOURCES.txt
python3.5.egg-info/dependency_links.txt
python3.5.egg-info/top_level.txt
python3_5/__init__.py
python3_5/tm.py