Metadata-Version: 2.1
Name: python3.5
Version: 0.1.0
Summary: A package with useful time utilities 2 
Author: Alex Stones
Author-email: figaro34figaro89@gmail.com
Keywords: utils,system
Requires-Python: >=3.7
